{
  "main": {
    "id": "30b1c16cf0adcd10",
    "type": "split",
    "children": [
      {
        "id": "a8ecb452b01c1375",
        "type": "tabs",
        "dimension": 50.98039215686274,
        "children": [
          {
            "id": "36c0d97c18c3361b",
            "type": "leaf",
            "state": {
              "type": "markdown",
              "state": {
                "file": "Notes/Herra Hjildrum.md",
                "mode": "source",
                "backlinks": true,
                "source": false
              }
            }
          }
        ]
      },
      {
        "id": "0a67d8aade14a607",
        "type": "tabs",
        "dimension": 49.01960784313726,
        "children": [
          {
            "id": "f719b7a10b31c932",
            "type": "leaf",
            "state": {
              "type": "empty",
              "state": {}
            }
          }
        ]
      }
    ],
    "direction": "vertical"
  },
  "left": {
    "id": "450114a5b9d5ea67",
    "type": "split",
    "children": [
      {
        "id": "14a358be6667255f",
        "type": "tabs",
        "dimension": 50.224719101123604,
        "children": [
          {
            "id": "a30fd3617025e07a",
            "type": "leaf",
            "state": {
              "type": "file-explorer",
              "state": {
                "sortOrder": "alphabetical"
              }
            }
          },
          {
            "id": "671af52291bc6115",
            "type": "leaf",
            "state": {
              "type": "BC-matrix",
              "state": {}
            }
          },
          {
            "id": "26b200db630638dc",
            "type": "leaf",
            "state": {
              "type": "bookmarks",
              "state": {}
            }
          },
          {
            "id": "28a1a5faf27384b7",
            "type": "leaf",
            "state": {
              "type": "search",
              "state": {
                "query": "",
                "matchingCase": false,
                "explainSearch": false,
                "collapseAll": false,
                "extraContext": false,
                "sortOrder": "alphabetical"
              }
            }
          }
        ]
      },
      {
        "id": "4191a5e500debdd1",
        "type": "tabs",
        "dimension": 49.775280898876396,
        "children": [
          {
            "id": "64497da9f1936a60",
            "type": "leaf",
            "state": {
              "type": "tagfolder-view",
              "state": {}
            }
          },
          {
            "id": "6dcf187b8a5dec41",
            "type": "leaf",
            "state": {
              "type": "BC-ducks",
              "state": {}
            }
          },
          {
            "id": "7a2f17f1a73bbb21",
            "type": "leaf",
            "state": {
              "type": "git-view",
              "state": {}
            }
          },
          {
            "id": "0a60b6b9792e56e8",
            "type": "leaf",
            "state": {
              "type": "git-history-view",
              "state": {}
            }
          }
        ]
      }
    ],
    "direction": "horizontal",
    "width": 200
  },
  "right": {
    "id": "5e987266027bf10b",
    "type": "split",
    "children": [
      {
        "id": "e9a54f3bc28ad751",
        "type": "tabs",
        "children": [
          {
            "id": "d8362b1add5293aa",
            "type": "leaf",
            "state": {
              "type": "backlink",
              "state": {
                "file": "Notes/Herra Hjildrum.md",
                "collapseAll": false,
                "extraContext": true,
                "sortOrder": "alphabetical",
                "showSearch": false,
                "searchQuery": "",
                "backlinkCollapsed": false,
                "unlinkedCollapsed": true
              }
            }
          },
          {
            "id": "2534af23f87eb96c",
            "type": "leaf",
            "state": {
              "type": "outgoing-link",
              "state": {
                "file": "Notes/Herra Hjildrum.md",
                "linksCollapsed": false,
                "unlinkedCollapsed": true
              }
            }
          },
          {
            "id": "a8e0ae93fec0f58c",
            "type": "leaf",
            "state": {
              "type": "BC-tree",
              "state": {}
            }
          },
          {
            "id": "db054626f38d2ad2",
            "type": "leaf",
            "state": {
              "type": "juggl_nodes",
              "state": {}
            }
          },
          {
            "id": "d97738f6835f2fc0",
            "type": "leaf",
            "state": {
              "type": "juggl_style",
              "state": {}
            }
          }
        ],
        "currentTab": 2
      }
    ],
    "direction": "horizontal",
    "width": 233.5,
    "collapsed": true
  },
  "left-ribbon": {
    "hiddenItems": {
      "obsidian-leaflet-plugin:Open Leaflet Map": true,
      "switcher:Open quick switcher": false,
      "canvas:Create new canvas": false,
      "templates:Insert template": false,
      "command-palette:Open command palette": false,
      "omnisearch:Omnisearch": false,
      "graph:Open graph view": false,
      "workspaces:Manage workspace layouts": false,
      "obsidian-excalidraw-plugin:Create new drawing": false,
      "obsidian-map-view:Open map view": false,
      "juggl:Juggl global graph": false,
      "templater-obsidian:Templater": false,
      "breadcrumbs:Breadcrumbs Visualisation": false
    }
  },
  "active": "36c0d97c18c3361b",
  "lastOpenFiles": [
    "Notes/Alton.md",
    "Notes/Varkainkilta.md",
    "Notes/Elhe.md",
    "Resources/jumalhovi.png",
    "Resources/Sôru-agazin kartta.png",
    "Resources/Shûlumir kartta.png",
    "Resources/Elhen vasara.png",
    "Resources/Selemdûr kartta.png",
    "Resources/Elhen Imperiumin läntinen kartta.png",
    "Resources/Sôru-agazin riimu.png",
    "Resources/Länsi-Lakeuden kartta.png",
    "Resources",
    "untitled folder",
    "Maps",
    "QGIS/Mountains/Borders/politicalunits.shx",
    "QGIS/Mountains/Borders/politicalunits.shp",
    "QGIS/Mountains/Borders/politicalunits.qix",
    "QGIS/Mountains/Borders/politicalunits.prj",
    "QGIS/Mountains/Borders/politicalunits.dbf",
    "QGIS/Mountains/Borders/politicalunits.cpg",
    "QGIS/Rivers/Rivers.shx",
    "Esihistoria.md",
    "Notes/Ûhm-gwe.md",
    "Notes/index.md",
    "Notes/Zahhak A'jabar.md",
    "Notes/Yuhzus.md",
    "Notes/Ya’ar.md",
    "Notes/Werdaeg.md",
    "Notes/Vuotava Kolpakko.md",
    "Notes/Vuorimaat.md",
    "Notes/Vuohiäiti.md",
    "Notes/Veli Galindus.md",
    "Notes/Vaskilaiset.md",
    "Notes/Vanhuksen kirjasto.md",
    "Notes/Vanhat jumalat.md",
    "Notes/Vaka-Viisi.md",
    "Notes/Uurmsvaltin haltijasuku.md",
    "Notes/Ulthâzin akolyytit.md",
    "Notes/Ulthâz.md",
    "Notes/Tähtitieteilijän muistiinpanot.md",
    "Notes/Tupa Duuri.md",
    "Notes/Tuoneteer.md",
    "Notes/Traakkilainen imperiumi.md",
    "Notes/Thivratassa.md",
    "Tärkeät tapahtumat.canvas",
    "Untitled.canvas",
    "Maps/Sôru-agazin kartta.png",
    "Sôru-agazin kartta.png"
  ]
}